odoo/addons/pos_category_vertical_display/README.rst
odoo/addons/pos_category_vertical_display/__init__.py
odoo/addons/pos_category_vertical_display/__manifest__.py
odoo/addons/pos_category_vertical_display/i18n/ca.po
odoo/addons/pos_category_vertical_display/i18n/es.po
odoo/addons/pos_category_vertical_display/i18n/it.po
odoo/addons/pos_category_vertical_display/i18n/pos_category_vertical_display.pot
odoo/addons/pos_category_vertical_display/readme/CONTRIBUTORS.md
odoo/addons/pos_category_vertical_display/readme/DESCRIPTION.md
odoo/addons/pos_category_vertical_display/static/description/icon.png
odoo/addons/pos_category_vertical_display/static/description/icon.svg
odoo/addons/pos_category_vertical_display/static/description/index.html
odoo/addons/pos_category_vertical_display/static/src/xml/category_selector.xml
odoo_addon_pos_category_vertical_display-17.0.1.0.0.4.dist-info/METADATA
odoo_addon_pos_category_vertical_display-17.0.1.0.0.4.dist-info/WHEEL
odoo_addon_pos_category_vertical_display-17.0.1.0.0.4.dist-info/top_level.txt
odoo_addon_pos_category_vertical_display-17.0.1.0.0.4.dist-info/RECORD
